{
	"backtraceGraph" : 
	{
		"commands" : 
		[
			"install"
		],
		"files" : 
		[
			"src/motioncore/CMakeLists.txt"
		],
		"nodes" : 
		[
			{
				"file" : 0
			},
			{
				"command" : 0,
				"file" : 0,
				"line" : 140,
				"parent" : 0
			},
			{
				"command" : 0,
				"file" : 0,
				"line" : 147,
				"parent" : 0
			}
		]
	},
	"installers" : 
	[
		{
			"backtrace" : 1,
			"component" : "Unspecified",
			"destination" : "lib",
			"paths" : 
			[
				"lib/libmotion.a"
			],
			"targetId" : "motion::@b461c9499611823db302",
			"targetIndex" : 6,
			"type" : "target"
		},
		{
			"backtrace" : 2,
			"component" : "Unspecified",
			"destination" : "include",
			"paths" : 
			[
				"src/motioncore"
			],
			"type" : "directory"
		}
	],
	"paths" : 
	{
		"build" : "src/motioncore",
		"source" : "src/motioncore"
	}
}
